{
  "project_info": {
    "project_number": "802100001314",
    "project_id": "souvenircadiz",
    "storage_bucket": "souvenircadiz.appspot.com"
  },
  "client": [
    {
      "client_info": {
        "mobilesdk_app_id": "1:802100001314:android:b4117da9ab55ba0db1287b",
        "android_client_info": {
          "package_name": "com.example.souvenirscadiz"
        }
      },
      "oauth_client": [
        {
          "client_id": "802100001314-0168qhbg5joqhv56bgjpf7ib4qbdotv0.apps.googleusercontent.com",
          "client_type": 3
        }
      ],
      "api_key": [
        {
          "current_key": "AIzaSyANp_eFcViuCZ57JSdD1LltX4kEp3q9458"
        }
      ],
      "services": {
        "appinvite_service": {
          "other_platform_oauth_client": [
            {
              "client_id": "802100001314-0168qhbg5joqhv56bgjpf7ib4qbdotv0.apps.googleusercontent.com",
              "client_type": 3
            }
          ]
        }
      }
    }
  ],
  "configuration_version": "1"
}